familiar.py
familiar/__init__.py
familiar/familiar.py
familiar/settings.py
familiar_tools/__init__.py
familiar_tools/familiar.py
familiar_tools/settings.py
familiar_tools/__pycache__/__init__.cpython-37.pyc
familiar_tools/__pycache__/familiar.cpython-37.pyc
familiar_tools/__pycache__/settings.cpython-37.pyc
src/__init__.py
src/familiar.py
src/settings.py
familiar-0.1.4.dist-info/LICENSE.txt
familiar-0.1.4.dist-info/METADATA
familiar-0.1.4.dist-info/WHEEL
familiar-0.1.4.dist-info/top_level.txt
familiar-0.1.4.dist-info/RECORD
